dead_function_finder/__init__.py
dead_function_finder/__main__.py
dead_function_finder/dead_function_finder.py
dead_function_finder/modules/__init__.py
dead_function_finder/modules/directory_parser.py
dead_function_finder/modules/function_finder.py
dead_function_finder/modules/function_search.py
dead_function_finder/modules/supported_languages.py
dead_function_finder-1.1.dist-info/LICENSE
dead_function_finder-1.1.dist-info/METADATA
dead_function_finder-1.1.dist-info/WHEEL
dead_function_finder-1.1.dist-info/entry_points.txt
dead_function_finder-1.1.dist-info/top_level.txt
dead_function_finder-1.1.dist-info/RECORD
