Metadata-Version: 2.1
Name: dead-function-finder
Version: 1.1
Summary: Utility to find dead functions within a codebase.
Home-page: https://github.com/gabfl/dead_function_finder
Author: Gabriel Bordeaux
Author-email: pypi@gab.lc
License: MIT
Classifier: Topic :: Database
Classifier: Topic :: Database :: Database Engines/Servers
Classifier: License :: OSI Approved :: MIT License
Classifier: Operating System :: MacOS
Classifier: Operating System :: POSIX :: Linux
Classifier: Natural Language :: English
Classifier: Programming Language :: Python :: 3
Classifier: Programming Language :: Python
Classifier: Development Status :: 4 - Beta
License-File: LICENSE
